videobgremover/__init__.py
videobgremover/__version__.py
videobgremover/py.typed
videobgremover/client/__init__.py
videobgremover/client/api.py
videobgremover/client/models.py
videobgremover/core/__init__.py
videobgremover/core/types.py
videobgremover/media/__init__.py
videobgremover/media/_importer_internal.py
videobgremover/media/backgrounds.py
videobgremover/media/composition.py
videobgremover/media/context.py
videobgremover/media/encoders.py
videobgremover/media/foregrounds.py
videobgremover/media/remove_bg.py
videobgremover/media/video.py
videobgremover/media/video_source.py
videobgremover-0.1.10.dist-info/METADATA
videobgremover-0.1.10.dist-info/WHEEL
videobgremover-0.1.10.dist-info/licenses/LICENSE
videobgremover-0.1.10.dist-info/RECORD
