Metadata-Version: 2.4
Name: videobgremover
Version: 0.1.10
Summary: Official Python SDK for VideoBGRemover API - Remove video backgrounds with AI and compose videos with FFmpeg
Project-URL: Homepage, https://videobgremover.com
Project-URL: Documentation, https://docs.videobgremover.com
Project-URL: Repository, https://github.com/videobgremover/videobgremover-python
Project-URL: Issues, https://github.com/videobgremover/videobgremover-python/issues
Author-email: Paul <paul@videobgremover.com>
License-File: LICENSE
Requires-Python: >=3.9
Requires-Dist: pydantic>=2.11.9
Requires-Dist: requests>=2.32.5
Provides-Extra: dev
Requires-Dist: build>=1.3.0; extra == 'dev'
Requires-Dist: mypy>=1.18.2; extra == 'dev'
Requires-Dist: pytest-asyncio>=0.24.0; extra == 'dev'
Requires-Dist: pytest-mock>=3.12.0; extra == 'dev'
Requires-Dist: pytest>=8.4.2; extra == 'dev'
Requires-Dist: python-dotenv>=1.0.0; extra == 'dev'
Requires-Dist: responses>=0.24.0; extra == 'dev'
Requires-Dist: ruff>=0.13.1; extra == 'dev'
Requires-Dist: twine>=6.2.0; extra == 'dev'
Requires-Dist: types-requests>=2.31.0; extra == 'dev'
